yeod/__init__.py
yeod/base.py
yeod/fundamentals.py
yeod/multi.py
yeod/shared.py
yeod/ticker.py
yeod/tickers.py
yeod/utils.py
yeod-0.1.14.dist-info/LICENSE
yeod-0.1.14.dist-info/LICENSE.txt
yeod-0.1.14.dist-info/METADATA
yeod-0.1.14.dist-info/WHEEL
yeod-0.1.14.dist-info/entry_points.txt
yeod-0.1.14.dist-info/top_level.txt
yeod-0.1.14.dist-info/RECORD
