Metadata-Version: 2.1
Name: yeod
Version: 0.1.14
Summary: eodhistoricaldata download
Home-page: https://github.com/matsvitt/yeod
Author: Matthias Vitt
Author-email: matthias.vitt@gmail.com
License: Apache
Keywords: pandas,eod,pandas datareader
Platform: any
Classifier: License :: OSI Approved :: Apache Software License
Classifier: Development Status :: 5 - Production/Stable
Classifier: Operating System :: OS Independent
Classifier: Intended Audience :: Developers
Classifier: Topic :: Office/Business :: Financial
Classifier: Topic :: Office/Business :: Financial :: Investment
Classifier: Topic :: Scientific/Engineering :: Interface Engine/Protocol Translator
Classifier: Topic :: Software Development :: Libraries
Classifier: Topic :: Software Development :: Libraries :: Python Modules
Classifier: Programming Language :: Python :: 2.7
Classifier: Programming Language :: Python :: 3.4
Classifier: Programming Language :: Python :: 3.5
Classifier: Programming Language :: Python :: 3.6
Classifier: Programming Language :: Python :: 3.7
Requires-Dist: pandas (>=0.24)
Requires-Dist: numpy (>=1.15)
Requires-Dist: requests (>=2.20)
Requires-Dist: multitasking (>=0.0.7)
Requires-Dist: lxml (>=4.5.1)
